tpcollections/__init__.py
tpcollections/_db.py
tpcollections/_mapping.py
tpcollections/_serializers.py
tpcollections/_util.py
tpcollections/py.typed
tpcollections-0.1.1.dist-info/LICENSE
tpcollections-0.1.1.dist-info/LICENSE.apache
tpcollections-0.1.1.dist-info/LICENSE.rst
tpcollections-0.1.1.dist-info/WHEEL
tpcollections-0.1.1.dist-info/METADATA
tpcollections-0.1.1.dist-info/RECORD
